websockify/__init__.py
websockify/__main__.py
websockify/auth_plugins.py
websockify/sysloghandler.py
websockify/token_plugins.py
websockify/websocket.py
websockify/websocketproxy.py
websockify/websocketserver.py
websockify/websockifyserver.py
websockify-0.12.0.dist-info/COPYING
websockify-0.12.0.dist-info/METADATA
websockify-0.12.0.dist-info/WHEEL
websockify-0.12.0.dist-info/entry_points.txt
websockify-0.12.0.dist-info/top_level.txt
websockify-0.12.0.dist-info/RECORD
