Metadata-Version: 2.1
Name: websockify
Version: 0.12.0
Summary: Websockify.
Home-page: https://github.com/novnc/websockify
Author: Joel Martin
Author-email: github@martintribe.org
License: LGPLv3
Keywords: noVNC websockify
Classifier: Programming Language :: Python
Classifier: Programming Language :: Python :: 3
Classifier: Programming Language :: Python :: 3 :: Only
Classifier: Programming Language :: Python :: 3.4
Classifier: Programming Language :: Python :: 3.5
Classifier: Programming Language :: Python :: 3.6
Classifier: Programming Language :: Python :: 3.7
Classifier: Programming Language :: Python :: 3.8
Classifier: Programming Language :: Python :: 3.9
License-File: COPYING
Requires-Dist: numpy
Requires-Dist: requests
Requires-Dist: jwcrypto
Requires-Dist: redis
